{
  "terms": [
    {
      "term": "Վիմագիր",
      "definition": "Ընդհանուր տերմին բոլոր քարե արձանագրությունների համար (Epigraph / petroglyph – a general term for all stone inscriptions)",
      "extractions": [
        {
          "file_name": "Divan_Prak10",
          "page_number": 13,
          "term": "վիմագրերին",
          "context": "առանձին հուշարձանների վիմագրերին հոդվածներ նվիրեցին հնագետ հովսեփ"
        },
        {
          "file_name": "Divan_Prak10",
          "page_number": 13,
          "term": "վիմագրերից",
          "context": "արևմտյան նիրակի վիմագրերից շատերը տեղ են գտել հիմնականում"
        },
        {
          "file_name": "Divan_Prak10",
          "page_number": 13,
          "term": "վիմագրերի",
          "context": "վերծանությամբ տրված վիմագրերի քանակական պատկերը հետեյալն է"
        },
        {
          "file_name": "Divan_Prak10",
          "page_number": 13,
          "term": "վիմագրերի",
          "context": "չենհամապատասխանում վիմագրերի գիտական հրապարակման դիվանյան"
        },
        {
          "file_name": "Divan_Prak10",
          "page_number": 14,
          "term": "վիմագրերից",
          "context": "վիմագրերից որոշները տեղ են գտել սկրտիչ էմինի անիի"
        },
        {
          "file_name": "Divan_Prak10",
          "page_number": 14,
          "term": "վիմագրերն",
          "context": "շրջակայքի վիմագրերն ամփոփող հատորում 11 արձ թարգմանված"
        },
        {
          "file_name": "Divan_Prak10",
          "page_number": 14,
          "term": "վիմագրերն",
          "context": "մրենի վիմագրերն առավել ամբողջական ուգրեթե դիվան"
        },
        {
          "file_name": "Divan_Prak10",
          "page_number": 14,
          "term": "վիմագրեր",
          "context": "ճարտարապետ արմեն ղազարյանը լուսանկա րել է տեղի մի շարք վիմագրեր ու պատրաստել"
        },
        {
          "file_name": "Divan_Prak10",
          "page_number": 14,
          "term": "վիմագրեր",
          "context": "վրիպած կամ տարընթերցումներ պարունակող մի քանի վիմագրեր նաև"
        },
        {
          "file_name": "Divan_Prak10",
          "page_number": 14,
          "term": "վիմագիր",
          "context": "աշխատության մեջ ընդգրկված է 54 վիմագիր16"
        },
        {
          "file_name": "Divan_Prak10",
          "page_number": 14,
          "term": "վիմագրերը",
          "context": "սամվել կարապետյանի ... հոռոմոսի վանքի վիմագրերը ուսումնասիրությունը որտեղ"
        },
        {
          "file_name": "Divan_Prak10",
          "page_number": 14,
          "term": "վիմագիր",
          "context": "դարձյալ նույն սկզբունքով ... բագնայրի վանքից 50 վիմագիր ա"
        },
        {
          "file_name": "Divan_Prak10",
          "page_number": 16,
          "term": "վիմագրերը",
          "context": "աշ մանուչարյան խաչի ձորի վիմագրերը ծիրակի պատմամշակութային"
        },
        {
          "file_name": "Divan_Prak10",
          "page_number": 16,
          "term": "վիմագրերը",
          "context": "աշ մանուչարյան երերույքի տաճարի վիմագրերը հին Հայաստանի"
        },
        {
          "file_name": "Divan_Prak10",
          "page_number": 16,
          "term": "վիմագրեր",
          "context": "հուսիկ մելքոնյան դարի վիմագրեր նոր կյանք գյուղից"
        },
        {
          "file_name": "Divan_Prak10",
          "page_number": 16,
          "term": "վիմագրեր",
          "context": "աղազարյան ... և որոշ վիմագրեր պբհ 2015 1"
        }
      ]
    },
    {
      "term": "վիմական արձանագրություն",
      "definition": "Ընդհանուր տերմին բոլոր քարե արձանագրությունների համար (Epigraph / petroglyph – a general term for all stone inscriptions)",
      "extractions": [
        {
          "file_name": "Divan_Prak10",
          "page_number": 15,
          "term": "վիմական արձանագրությունների",
          "context": "ավագյան ... վիմական արձանագրությունների բառաքննություն Երևան 1978"
        }
      ]
    },
    {
      "term": "Շինարարական արձանագրություն",
      "definition": "Շինարարության կամ վերանորոգման արձանագրություններ",
      "extractions": [
        {
          "file_name": "Divan_Prak10",
          "page_number": 15,
          "term": "շինարարական արձա նագրություններ",
          "context": "սանուչարյան նիրակի չհոապարակված շինարարական արձա նագրություններ լրաբեր"
        }
      ]
    }
  ]
}